aws_util/__init__.py
aws_util/aws.py
aws_util/pyspark.py
david_aws_util-1.1.4.dist-info/METADATA
david_aws_util-1.1.4.dist-info/WHEEL
david_aws_util-1.1.4.dist-info/entry_points.txt
david_aws_util-1.1.4.dist-info/top_level.txt
david_aws_util-1.1.4.dist-info/RECORD
