Metadata-Version: 2.4
Name: david_aws_util
Version: 1.1.4
Summary: david's aws util
Home-page: https://github.com/simon-asis/aws_util
Author: david
Author-email: tingyoon@gmail.com
License: MIT License
Classifier: Programming Language :: Python :: 3
Classifier: License :: OSI Approved :: MIT License
Classifier: Operating System :: OS Independent
Requires-Python: >=3.8,<3.13
Requires-Dist: boto3<2.0,>=1.20.0
Requires-Dist: pandas==1.3.5
Provides-Extra: extra
Dynamic: author
Dynamic: author-email
Dynamic: classifier
Dynamic: description
Dynamic: description-content-type
Dynamic: home-page
Dynamic: license
Dynamic: provides-extra
Dynamic: requires-dist
Dynamic: requires-python
Dynamic: summary
